README.rst
setup.cfg
setup.py
streak_client/__init__.py
streak_client/streak_client.py
streak_client/streak_objects.py
streak_client.egg-info/PKG-INFO
streak_client.egg-info/SOURCES.txt
streak_client.egg-info/dependency_links.txt
streak_client.egg-info/not-zip-safe
streak_client.egg-info/requires.txt
streak_client.egg-info/top_level.txt