Metadata-Version: 1.1
Name: streak-client
Version: 0.2.1
Summary: simple flat client class for streak.com api with helper objects
Home-page: http://github.com/mehmetg/streak_client
Author: Mehmet Gerceker
Author-email: mehmetg@msn.com
License: MIT
Keywords: streak,api
Platform: UNKNOWN
Classifier: Development Status :: 4 - Beta
Classifier: Topic :: Software Development :: Libraries :: Python Modules
Classifier: License :: OSI Approved :: MIT License
Classifier: Operating System :: MacOS
Classifier: Operating System :: Microsoft :: Windows
Classifier: Operating System :: POSIX
Classifier: Programming Language :: Python
Classifier: Programming Language :: Python :: 2
Classifier: Programming Language :: Python :: 3
